pythcalculus
