Metadata-Version: 2.1
Name: pythcalculus
Version: 0.5
Summary: Integrate and Differentiate over here!
Home-page: https://github.com/vaish1999/Calculus-in-python
Author: Vaishakh Nargund
Author-email: vaishakh.nargund1999@gmail.com
License: GPL 2.0
Download-URL: https://github.com/vaish1999/Calculus-in-python/archive/v1.4.tar.gz
Keywords: calculus,python,differentiate,integrate,derivative
Platform: UNKNOWN
Classifier: Development Status :: 3 - Alpha
Classifier: Intended Audience :: Developers
Classifier: Topic :: Software Development :: Build Tools
Classifier: License :: OSI Approved :: GNU General Public License v2 (GPLv2)
Classifier: Programming Language :: Python :: 3
Classifier: Programming Language :: Python :: 3.4
Classifier: Programming Language :: Python :: 3.5
Classifier: Programming Language :: Python :: 3.6
Classifier: Programming Language :: Python :: 3.7
